<?xml version="1.0"?>
<relationship xmlns:xsi="http://www.w3.org/2001/XMLSchema-instance" xmlns:xsd="http://www.w3.org/2001/XMLSchema" id="f2247033-d3f0-4de9-939d-b995c84f5d04" lastModifiedUtc="2012-05-14T14:21:44.8559395Z" parentEntityId="750a7f26-3604-467b-94fe-249370231df4" childEntityId="ecdf574f-89a4-4bee-849c-0c4282cd0fc2">
  <extendedMetaData />
  <ExtendedPropertiesCollection>
    <extendee type="Sage.Platform.Orm.Entities.OrmRelationship" />
  </ExtendedPropertiesCollection>
  <parentProperty id="15d8176b-dec9-483d-a5ed-b0e0b957387e" lastModifiedUtc="2012-05-14T14:21:42.6998275Z" name="EMCampaignConClicks" audited="false">
    <ExtendedPropertiesCollection>
      <extendee type="Sage.Platform.Orm.Entities.OrmRelationProperty">
        <extender guid="ae60621d-9d91-3d9a-b9fb-eb6c8be12131">
          <OrmEntityPropertySDataExtension generate="true" />
        </extender>
      </extendee>
    </ExtendedPropertiesCollection>
    <SystemDataType guid="2f770d03-c93c-4605-8ae8-7cdae04830d7">
      <RelationshipDataType />
    </SystemDataType>
  </parentProperty>
  <childProperty id="6b560263-a499-4c9e-9852-431ceb550a04" lastModifiedUtc="2012-05-14T14:21:42.6998275Z" name="Contact" audited="false">
    <ExtendedPropertiesCollection>
      <extendee type="Sage.Platform.Orm.Entities.OrmRelationProperty">
        <extender guid="ae60621d-9d91-3d9a-b9fb-eb6c8be12131">
          <OrmEntityPropertySDataExtension generate="true" />
        </extender>
      </extendee>
    </ExtendedPropertiesCollection>
    <SystemDataType guid="2f770d03-c93c-4605-8ae8-7cdae04830d7">
      <RelationshipDataType />
    </SystemDataType>
  </childProperty>
  <column>
    <OrmRelationshipColumn id="5e1aa3a1-8f2d-417b-8ffc-baef5cfb8369" parentPropertyId="67fe9234-a814-4d79-a813-01046c1ae19d" childPropertyId="24cb84fb-b4e2-40af-8bf2-60dae43b683b" ordinal="0" />
  </column>
</relationship>